trdi_adcp_readers/__init__.py
trdi_adcp_readers/readers.py
trdi_adcp_readers/pd0/__init__.py
trdi_adcp_readers/pd0/pd0_parser.py
trdi_adcp_readers/pd15/__init__.py
trdi_adcp_readers/pd15/pd0_converters.py
trdi_adcp_readers/scripts/__init__.py
trdi_adcp_readers/scripts/convert_trdi.py
trdi_adcp_readers/scripts/convert_trdi_uhi.py
trdi_adcp_readers-25.6.4.dist-info/METADATA
trdi_adcp_readers-25.6.4.dist-info/WHEEL
trdi_adcp_readers-25.6.4.dist-info/entry_points.txt
trdi_adcp_readers-25.6.4.dist-info/licenses/LICENSE.txt
trdi_adcp_readers-25.6.4.dist-info/RECORD
