Metadata-Version: 2.4
Name: trdi_adcp_readers
Version: 25.6.4
Summary: A library capable of reading various TRDI ADCP data formats including PD15 and PD0 into python native types.
Project-URL: Homepage, https://github.com/USF-COT/trdi_adcp_readers
Author: USF CMS Ocean Technology Group
Maintainer-email: Michael Lindemuth <lindemuth@gmail.com>
License: MIT
License-File: LICENSE.txt
Requires-Python: >=3.7
